monotonic_binning/__init__.py
monotonic_binning/monotonic_woe_binning.py
monotonic_binning-0.0.1.dist-info/LICENSE
monotonic_binning-0.0.1.dist-info/METADATA
monotonic_binning-0.0.1.dist-info/WHEEL
monotonic_binning-0.0.1.dist-info/top_level.txt
monotonic_binning-0.0.1.dist-info/RECORD
